ringtheory/__init__.py
ringtheory/core.py
ringtheory/gpu_optimizer.py
ringtheory/monitor.py
ringtheory/utils.py
ringtheory-1.0.110.dist-info/licenses/LICENSE.md
ringtheory-1.0.110.dist-info/METADATA
ringtheory-1.0.110.dist-info/WHEEL
ringtheory-1.0.110.dist-info/top_level.txt
ringtheory-1.0.110.dist-info/RECORD
