Metadata-Version: 2.4
Name: ringtheory
Version: 1.0.110
Summary: Energy-efficient GPU/CPU computing using quantum-inspired ring patterns
Home-page: https://arkhipsoft.ru/Article/ID?num=89
Author: RingTheory AI
Author-email: vipvodu@yandex.ru
License: Proprietary
Keywords: energy-efficiency,gpu-optimization,crypto-mining,quantum-computing,ring-theory,ai-optimization,data-center
Classifier: Development Status :: 5 - Production/Stable
Classifier: Intended Audience :: Science/Research
Classifier: Intended Audience :: Developers
Classifier: Intended Audience :: Financial and Insurance Industry
Classifier: Topic :: Scientific/Engineering :: Artificial Intelligence
Classifier: Topic :: Scientific/Engineering :: Physics
Classifier: Topic :: System :: Hardware
Classifier: License :: Other/Proprietary License
Classifier: Programming Language :: Python :: 3
Classifier: Operating System :: OS Independent
Requires-Python: >=3.7
License-File: LICENSE.md
Requires-Dist: numpy>=1.19.0
Requires-Dist: psutil>=5.8.0
Provides-Extra: gpu
Requires-Dist: torch>=1.9.0; extra == "gpu"
Provides-Extra: mining
Requires-Dist: torch>=1.9.0; extra == "mining"
Provides-Extra: full
Requires-Dist: torch>=1.9.0; extra == "full"
Requires-Dist: matplotlib>=3.3.0; extra == "full"
Requires-Dist: pandas>=1.3.0; extra == "full"
Dynamic: author
Dynamic: author-email
Dynamic: classifier
Dynamic: description
Dynamic: description-content-type
Dynamic: home-page
Dynamic: keywords
Dynamic: license
Dynamic: license-file
Dynamic: provides-extra
Dynamic: requires-dist
Dynamic: requires-python
Dynamic: summary
